bfencryption/__init__.py
bfencryption/util.py
bfencryption-0.1.5.dist-info/LICENSE
bfencryption-0.1.5.dist-info/METADATA
bfencryption-0.1.5.dist-info/WHEEL
bfencryption-0.1.5.dist-info/top_level.txt
bfencryption-0.1.5.dist-info/RECORD
