Metadata-Version: 2.1
Name: bfencryption
Version: 0.1.5
Summary: A encryption which decrypts using brute force.
Author-email: "Aino L. Spring" <info@aino-spring.com>
Project-URL: Homepage, https://github.com/AinoSpring/bfencryption
Project-URL: Bug Tracker, https://github.com/AinoSpring/bfencryption/issues
Classifier: Programming Language :: Python :: 3
Classifier: License :: OSI Approved :: MIT License
Classifier: Operating System :: OS Independent
Requires-Python: >=3.7
License-File: LICENSE
